pymfe/__init__.py
pymfe/_bootstrap.py
pymfe/_dev.py
pymfe/_internal.py
pymfe/_summary.py
pymfe/_utils.py
pymfe/_version.py
pymfe/clustering.py
pymfe/complexity.py
pymfe/concept.py
pymfe/general.py
pymfe/info_theory.py
pymfe/itemset.py
pymfe/landmarking.py
pymfe/mfe.py
pymfe/model_based.py
pymfe/relative.py
pymfe/scoring.py
pymfe/statistical.py
tests/__init__.py
tests/test_architecture.py
tests/test_clustering.py
tests/test_complexity.py
tests/test_concept.py
tests/test_errors_warnings.py
tests/test_general.py
tests/test_infotheo.py
tests/test_itemset.py
tests/test_landmarking.py
tests/test_model_based.py
tests/test_output.py
tests/test_relative_landmarking.py
tests/test_scaling.py
tests/test_scoring.py
tests/test_statistical.py
tests/test_summary.py
tests/test_system_testing.py
tests/utils.py
pymfe-0.4.4.dist-info/LICENCE
pymfe-0.4.4.dist-info/METADATA
pymfe-0.4.4.dist-info/WHEEL
pymfe-0.4.4.dist-info/top_level.txt
pymfe-0.4.4.dist-info/RECORD
