Metadata-Version: 2.1
Name: pymfe
Version: 0.4.4
Summary: Meta-feature Extractor
Home-page: https://github.com/ealcobaca/pymfe
Download-URL: https://github.com/ealcobaca/pymfe/releases
Maintainer: Edesio Alcobaça, Felipe Alves Siqueira
Maintainer-email: edesio@usp.br, felipe.siqueira@usp.br
License: MIT
Classifier: Intended Audience :: Science/Research
Classifier: Intended Audience :: Developers
Classifier: License :: OSI Approved :: MIT License
Classifier: Natural Language :: English
Classifier: Programming Language :: Python
Classifier: Topic :: Software Development
Classifier: Topic :: Scientific/Engineering
Classifier: Operating System :: OS Independent
Classifier: Programming Language :: Python :: 3.6
Classifier: Programming Language :: Python :: 3.7
Classifier: Programming Language :: Python :: 3.8
Classifier: Programming Language :: Python :: 3.9
License-File: LICENCE
Requires-Dist: numpy
Requires-Dist: scipy
Requires-Dist: scikit-learn
Requires-Dist: patsy
Requires-Dist: pandas
Requires-Dist: statsmodels
Requires-Dist: texttable
Requires-Dist: tqdm
Requires-Dist: igraph>=0.10.1
Requires-Dist: gower
Provides-Extra: code-check
Requires-Dist: pytest; extra == "code-check"
Requires-Dist: mypy; extra == "code-check"
Requires-Dist: liac-arff; extra == "code-check"
Requires-Dist: flake8; extra == "code-check"
Requires-Dist: pylint; extra == "code-check"
Provides-Extra: docs
Requires-Dist: sphinx; extra == "docs"
Requires-Dist: sphinx-gallery; extra == "docs"
Requires-Dist: sphinx-rtd-theme; extra == "docs"
Requires-Dist: numpydoc; extra == "docs"
Requires-Dist: liac-arff; extra == "docs"
Provides-Extra: tests
Requires-Dist: pytest; extra == "tests"
Requires-Dist: pytest-cov; extra == "tests"
Requires-Dist: pytest-xdist; extra == "tests"
Requires-Dist: liac-arff; extra == "tests"
